pytest_wake/__init__.py
pytest_wake/client.py
pytest_wake/core.py
pytest_wake/exception.py
pytest_wake/signature.py
pytest_wake/utils.py
pytest_wake-0.4.3.dist-info/LICENSE
pytest_wake-0.4.3.dist-info/METADATA
pytest_wake-0.4.3.dist-info/WHEEL
pytest_wake-0.4.3.dist-info/entry_points.txt
pytest_wake-0.4.3.dist-info/top_level.txt
pytest_wake-0.4.3.dist-info/RECORD
