Metadata-Version: 2.1
Name: pytest-wake
Version: 0.4.3
Home-page: 
Author: 
Author-email: 
Classifier: License :: OSI Approved :: Apache Software License
Classifier: Programming Language :: Python :: 3
Classifier: Programming Language :: Python :: 3.7
Classifier: Programming Language :: Python :: 3.8
Classifier: Programming Language :: Python :: 3.9
Classifier: Programming Language :: Python :: Implementation :: CPython
Classifier: Programming Language :: Python :: Implementation :: PyPy
Classifier: Framework :: Pytest
Requires-Python: >=3.6.0
License-File: LICENSE
Requires-Dist: pytest
